[
  {
    "name": "北京市",
    "url": "11.html",
    "code": "110000000000"
  },
  {
    "name": "天津市",
    "url": "12.html",
    "code": "120000000000"
  },
  {
    "name": "河北省",
    "url": "13.html",
    "code": "130000000000"
  },
  {
    "name": "山西省",
    "url": "14.html",
    "code": "140000000000"
  },
  {
    "name": "内蒙古自治区",
    "url": "15.html",
    "code": "150000000000"
  },
  {
    "name": "辽宁省",
    "url": "21.html",
    "code": "210000000000"
  },
  {
    "name": "吉林省",
    "url": "22.html",
    "code": "220000000000"
  },
  {
    "name": "黑龙江省",
    "url": "23.html",
    "code": "230000000000"
  },
  {
    "name": "上海市",
    "url": "31.html",
    "code": "310000000000"
  },
  {
    "name": "江苏省",
    "url": "32.html",
    "code": "320000000000"
  },
  {
    "name": "浙江省",
    "url": "33.html",
    "code": "330000000000"
  },
  {
    "name": "安徽省",
    "url": "34.html",
    "code": "340000000000"
  },
  {
    "name": "福建省",
    "url": "35.html",
    "code": "350000000000"
  },
  {
    "name": "江西省",
    "url": "36.html",
    "code": "360000000000"
  },
  {
    "name": "山东省",
    "url": "37.html",
    "code": "370000000000"
  },
  {
    "name": "河南省",
    "url": "41.html",
    "code": "410000000000"
  },
  {
    "name": "湖北省",
    "url": "42.html",
    "code": "420000000000"
  },
  {
    "name": "湖南省",
    "url": "43.html",
    "code": "430000000000"
  },
  {
    "name": "广东省",
    "url": "44.html",
    "code": "440000000000"
  },
  {
    "name": "广西壮族自治区",
    "url": "45.html",
    "code": "450000000000"
  },
  {
    "name": "海南省",
    "url": "46.html",
    "code": "460000000000"
  },
  {
    "name": "重庆市",
    "url": "50.html",
    "code": "500000000000"
  },
  {
    "name": "四川省",
    "url": "51.html",
    "code": "510000000000"
  },
  {
    "name": "贵州省",
    "url": "52.html",
    "code": "520000000000"
  },
  {
    "name": "云南省",
    "url": "53.html",
    "code": "530000000000"
  },
  {
    "name": "西藏自治区",
    "url": "54.html",
    "code": "540000000000"
  },
  {
    "name": "陕西省",
    "url": "61.html",
    "code": "610000000000"
  },
  {
    "name": "甘肃省",
    "url": "62.html",
    "code": "620000000000"
  },
  {
    "name": "青海省",
    "url": "63.html",
    "code": "630000000000"
  },
  {
    "name": "宁夏回族自治区",
    "url": "64.html",
    "code": "640000000000"
  },
  {
    "name": "新疆维吾尔自治区",
    "url": "65.html",
    "code": "650000000000"
  }
]